{"files":{"apps/crawler/dist/sources/japanese.js":{"size":13477,"mtime_nanos":1774576894326488014,"mode":438,"is_dir":false},"apps/crawler/dist/utils/rateLimiter.js":{"size":4486,"mtime_nanos":1774576894454488016,"mode":438,"is_dir":false},"apps/crawler/dist/sources/liveAction.js":{"size":4932,"mtime_nanos":1774576894409488015,"mode":438,"is_dir":false},"apps/crawler/dist/sources/series.js":{"size":4433,"mtime_nanos":1774576894400488015,"mode":438,"is_dir":false},"apps/crawler/dist/sources/chinese.js":{"size":7471,"mtime_nanos":1774576894338488014,"mode":438,"is_dir":false},"apps/crawler/dist/sources/manhwa.js":{"size":6693,"mtime_nanos":1774576894406488015,"mode":438,"is_dir":false},"apps/crawler/dist/utils/workers.js":{"size":5500,"mtime_nanos":1774576894462488016,"mode":438,"is_dir":false},"apps/crawler/dist/sources/anilist.js":{"size":2898,"mtime_nanos":1774576894278488013,"mode":438,"is_dir":false},"apps/crawler/dist/sources/sites.js":{"size":3982,"mtime_nanos":1774576894255488013,"mode":438,"is_dir":false},"apps/crawler/dist/sources/rumors.js":{"size":18516,"mtime_nanos":1774576894421488016,"mode":438,"is_dir":false},"apps/crawler/dist/sources/mangadex.js":{"size":3839,"mtime_nanos":1774576894301488013,"mode":438,"is_dir":false},"apps/crawler/dist/sources/jikan.js":{"size":2570,"mtime_nanos":1774576894289488013,"mode":438,"is_dir":false},"apps/crawler/dist/sources/rss.js":{"size":897,"mtime_nanos":1774576894236488012,"mode":438,"is_dir":false},"apps/crawler/dist/sources/manager.js":{"size":5871,"mtime_nanos":1774576894221488012,"mode":438,"is_dir":false},"apps/crawler/dist/sources/manga.js":{"size":13471,"mtime_nanos":1774576894364488015,"mode":438,"is_dir":false},"apps/crawler/dist/sources":{"size":0,"mtime_nanos":0,"mode":0,"is_dir":true},"apps/crawler/dist/sources/anime.js":{"size":1783,"mtime_nanos":1774576894345488014,"mode":438,"is_dir":false},"apps/crawler/.turbo/turbo-build.log":{"size":46,"mtime_nanos":1774576894507488017,"mode":438,"is_dir":false},"apps/crawler/dist/index.js":{"size":4283,"mtime_nanos":1774576894437488016,"mode":438,"is_dir":false},"apps/crawler/dist/sources/social.js":{"size":9817,"mtime_nanos":1774576894273488013,"mode":438,"is_dir":false},"apps/crawler/dist/utils":{"size":0,"mtime_nanos":0,"mode":0,"is_dir":true},"apps/crawler/dist/utils/cache.js":{"size":9908,"mtime_nanos":1774576894447488016,"mode":438,"is_dir":false},"apps/crawler/dist":{"size":0,"mtime_nanos":0,"mode":0,"is_dir":true},"apps/crawler/dist/utils/queue.js":{"size":1988,"mtime_nanos":1774576894433488016,"mode":438,"is_dir":false},"apps/crawler/dist/sources/kitsu.js":{"size":3135,"mtime_nanos":1774576894296488013,"mode":438,"is_dir":false},"apps/crawler/dist/sources/config.js":{"size":13039,"mtime_nanos":1774576894427488016,"mode":438,"is_dir":false},"apps/crawler/dist/sources/film.js":{"size":15268,"mtime_nanos":1774576894396488015,"mode":438,"is_dir":false}},"order":["apps/crawler/.turbo/turbo-build.log","apps/crawler/dist","apps/crawler/dist/index.js","apps/crawler/dist/sources","apps/crawler/dist/sources/anilist.js","apps/crawler/dist/sources/anime.js","apps/crawler/dist/sources/chinese.js","apps/crawler/dist/sources/config.js","apps/crawler/dist/sources/film.js","apps/crawler/dist/sources/japanese.js","apps/crawler/dist/sources/jikan.js","apps/crawler/dist/sources/kitsu.js","apps/crawler/dist/sources/liveAction.js","apps/crawler/dist/sources/manager.js","apps/crawler/dist/sources/manga.js","apps/crawler/dist/sources/mangadex.js","apps/crawler/dist/sources/manhwa.js","apps/crawler/dist/sources/rss.js","apps/crawler/dist/sources/rumors.js","apps/crawler/dist/sources/series.js","apps/crawler/dist/sources/sites.js","apps/crawler/dist/sources/social.js","apps/crawler/dist/utils","apps/crawler/dist/utils/cache.js","apps/crawler/dist/utils/queue.js","apps/crawler/dist/utils/rateLimiter.js","apps/crawler/dist/utils/workers.js"]}